<pkg-contents spec="1.12"><f n="Junction Networks Bulk Uploader.app" o="oren" g="wheel" p="16877" pt="/private/var/apps/jn_bulk_uploads/release/Junction Networks Bulk Uploader.app" m="false" t="file"><f n="Contents" o="oren" g="wheel" p="16877"><f n="Info.plist" o="oren" g="wheel" p="33188"/><f n="MacOS" o="oren" g="wheel" p="16877"><f n="JavaApplicationStub" o="oren" g="wheel" p="33261"/></f><f n="PkgInfo" o="oren" g="wheel" p="33188"/><f n="Resources" o="oren" g="wheel" p="16877"><f n="icon_onsip.icns" o="oren" g="wheel" p="33188"/><f n="Java" o="oren" g="wheel" p="16877"><f n="bulkuploader.jar" o="oren" g="wheel" p="33188"/><f n="BulkUserAdd-1.0-dependencies.jar" o="oren" g="wheel" p="33188"/><f n="mockito-all-1.8.5.jar" o="oren" g="wheel" p="33188"/></f></f></f></f></pkg-contents>